yfinance_extended/__init__.py
yfinance_extended/models.py
yfinance_extended/quote.py
yfinance_extended/version.py
yfinance_extended/utils/__init__.py
yfinance_extended/utils/yf_price_df.py
yfinance_extended-0.1.1.dist-info/licenses/LICENSE
yfinance_extended-0.1.1.dist-info/METADATA
yfinance_extended-0.1.1.dist-info/WHEEL
yfinance_extended-0.1.1.dist-info/top_level.txt
yfinance_extended-0.1.1.dist-info/RECORD
